location_util/__init__.py
location_util/dictionary_loader.py
location_util/location_parser.py
location_parse_lzx-0.0.3.dist-info/METADATA
location_parse_lzx-0.0.3.dist-info/WHEEL
location_parse_lzx-0.0.3.dist-info/top_level.txt
location_parse_lzx-0.0.3.dist-info/RECORD
